gluejobutils/__init__.py
gluejobutils/data/data_type_conversion.json
gluejobutils/datatypes.py
gluejobutils/df_transforms.py
gluejobutils/record_datetimes.py
gluejobutils/s3.py
gluejobutils/utils.py
gluejobutils-3.2.0.dist-info/WHEEL
gluejobutils-3.2.0.dist-info/METADATA
gluejobutils-3.2.0.dist-info/RECORD
